pycsspeechtts/__init__.py
pycsspeechtts/pycsspeechtts.py
pycsspeechtts/test.py
pycsspeechtts-1.0.7.dist-info/METADATA
pycsspeechtts-1.0.7.dist-info/WHEEL
pycsspeechtts-1.0.7.dist-info/licenses/LICENSE
pycsspeechtts-1.0.7.dist-info/RECORD
