Metadata-Version: 2.1
Name: pycsspeechtts
Version: 1.0.7
Summary: Python 3 interface to Microsoft Cognitive Services Text To Speech
Project-URL: Homepage, https://github.com/jeroenterheerdt/pycsspeechtts
Project-URL: Bug Tracker, https://github.com/jeroenterheerdt/pycsspeechtts/issues
Author: Jeroen ter Heerdt
License-File: LICENSE
Classifier: License :: OSI Approved :: MIT License
Classifier: Operating System :: OS Independent
Classifier: Programming Language :: Python :: 3
Requires-Python: >=3.7
